main.py
setup.py
kera_preprocessing.egg-info/PKG-INFO
kera_preprocessing.egg-info/SOURCES.txt
kera_preprocessing.egg-info/dependency_links.txt
kera_preprocessing.egg-info/requires.txt
kera_preprocessing.egg-info/top_level.txt